web_scrappingg/__init__.py
web_scrappingg-0.0.1.dist-info/LICENCE.txt
web_scrappingg-0.0.1.dist-info/METADATA
web_scrappingg-0.0.1.dist-info/WHEEL
web_scrappingg-0.0.1.dist-info/top_level.txt
web_scrappingg-0.0.1.dist-info/RECORD
