Metadata-Version: 2.1
Name: web-scrappingg
Version: 0.0.1
Summary: Weather Forecast without using API
Home-page: UNKNOWN
Author: Satya
Author-email: bsatyanreddy4@gmail.com
License: UNKNOWN
Platform: UNKNOWN
Classifier: Programming Language :: Python :: 3
Classifier: License :: OSI Approved :: MIT License
Classifier: Operating System :: OS Independent
